FLImagingClrPy/FLImagingClrPyLoader.py
FLImagingClrPy/__init__.py
flimagingclrpy-6.8.5.dist-info/METADATA
flimagingclrpy-6.8.5.dist-info/WHEEL
flimagingclrpy-6.8.5.dist-info/top_level.txt
flimagingclrpy-6.8.5.dist-info/RECORD
