Metadata-Version: 2.4
Name: FLImagingClrPy
Version: 6.8.5
Summary: FLImaging(R) CLR for Python
Author: Fourth Logic Incorporated
Author-email: Fourth Logic Incorporated <support@fourthlogic.co.kr>
License: MIT
Requires-Python: >=3.8.0
Requires-Dist: pythonnet>=3.0.5
Dynamic: author
Dynamic: requires-python
